Workbook

Sheet Start here
A1: Reseller bookkeeping spreadsheet
A3: One row per sale on the Sales sheet, one row per cost on the Expenses sheet. Grey columns work themselves out.
A4: • Sales: the date it sold, where, what, the order number, what the buyer paid, then the fees, postage and what you paid for the item.
A5: • Expenses: anything you bought to run the selling, such as packaging, printer labels, mileage to sourcing, or a subscription. Keep the receipt.
A6: • Summary: totals for the tax year you pick in cell B1, by platform and in total. The UK tax year runs 6 April to 5 April.
A7: Tip: download each platform's sales report monthly and copy the totals across, rather than typing every order by hand.
A8: The trading allowance, platform reporting and Self Assessment rules are explained, with links to GOV.UK, in the guide 'Bookkeeping and tax for UK resellers' on The Sellers Network.
A10: Free from The Sellers Network, a forum for UK resellers. Not tax, legal or financial advice.

Sheet Sales
A1: Date sold | B1: Platform | C1: Item | D1: Order number | E1: Buyer paid (inc. postage) | F1: Platform fees | G1: Postage cost | H1: Item cost | I1: Profit | J1: Tax year
I2: =IF(E2="","",E2-F2-G2-H2) | J2: =IF(A2="","",IF(A2>=DATE(YEAR(A2),4,6),YEAR(A2)&"-"&RIGHT(YEAR(A2)+1,2),YEAR(A2)-1&"-"&RIGHT(YEAR(A2),2)))
I3: =IF(E3="","",E3-F3-G3-H3) | J3: =IF(A3="","",IF(A3>=DATE(YEAR(A3),4,6),YEAR(A3)&"-"&RIGHT(YEAR(A3)+1,2),YEAR(A3)-1&"-"&RIGHT(YEAR(A3),2)))
I4: =IF(E4="","",E4-F4-G4-H4) | J4: =IF(A4="","",IF(A4>=DATE(YEAR(A4),4,6),YEAR(A4)&"-"&RIGHT(YEAR(A4)+1,2),YEAR(A4)-1&"-"&RIGHT(YEAR(A4),2)))
I5: =IF(E5="","",E5-F5-G5-H5) | J5: =IF(A5="","",IF(A5>=DATE(YEAR(A5),4,6),YEAR(A5)&"-"&RIGHT(YEAR(A5)+1,2),YEAR(A5)-1&"-"&RIGHT(YEAR(A5),2)))
I6: =IF(E6="","",E6-F6-G6-H6) | J6: =IF(A6="","",IF(A6>=DATE(YEAR(A6),4,6),YEAR(A6)&"-"&RIGHT(YEAR(A6)+1,2),YEAR(A6)-1&"-"&RIGHT(YEAR(A6),2)))
I7: =IF(E7="","",E7-F7-G7-H7) | J7: =IF(A7="","",IF(A7>=DATE(YEAR(A7),4,6),YEAR(A7)&"-"&RIGHT(YEAR(A7)+1,2),YEAR(A7)-1&"-"&RIGHT(YEAR(A7),2)))
I8: =IF(E8="","",E8-F8-G8-H8) | J8: =IF(A8="","",IF(A8>=DATE(YEAR(A8),4,6),YEAR(A8)&"-"&RIGHT(YEAR(A8)+1,2),YEAR(A8)-1&"-"&RIGHT(YEAR(A8),2)))
I9: =IF(E9="","",E9-F9-G9-H9) | J9: =IF(A9="","",IF(A9>=DATE(YEAR(A9),4,6),YEAR(A9)&"-"&RIGHT(YEAR(A9)+1,2),YEAR(A9)-1&"-"&RIGHT(YEAR(A9),2)))
I10: =IF(E10="","",E10-F10-G10-H10) | J10: =IF(A10="","",IF(A10>=DATE(YEAR(A10),4,6),YEAR(A10)&"-"&RIGHT(YEAR(A10)+1,2),YEAR(A10)-1&"-"&RIGHT(YEAR(A10),2)))
I11: =IF(E11="","",E11-F11-G11-H11) | J11: =IF(A11="","",IF(A11>=DATE(YEAR(A11),4,6),YEAR(A11)&"-"&RIGHT(YEAR(A11)+1,2),YEAR(A11)-1&"-"&RIGHT(YEAR(A11),2)))
I12: =IF(E12="","",E12-F12-G12-H12) | J12: =IF(A12="","",IF(A12>=DATE(YEAR(A12),4,6),YEAR(A12)&"-"&RIGHT(YEAR(A12)+1,2),YEAR(A12)-1&"-"&RIGHT(YEAR(A12),2)))
I13: =IF(E13="","",E13-F13-G13-H13) | J13: =IF(A13="","",IF(A13>=DATE(YEAR(A13),4,6),YEAR(A13)&"-"&RIGHT(YEAR(A13)+1,2),YEAR(A13)-1&"-"&RIGHT(YEAR(A13),2)))
... I501: =IF(E501="","",E501-F501-G501-H501) | J501: =IF(A501="","",IF(A501>=DATE(YEAR(A501),4,6),YEAR(A501)&"-"&RIGHT(YEAR(A501)+1,2),YEAR(A501)-1&"-"&RIGHT(YEAR(A501),2)))

Sheet Expenses
A1: Date | B1: Paid to | C1: What for | D1: Type | E1: Amount | F1: Receipt kept? | G1: Tax year
G2: =IF(A2="","",IF(A2>=DATE(YEAR(A2),4,6),YEAR(A2)&"-"&RIGHT(YEAR(A2)+1,2),YEAR(A2)-1&"-"&RIGHT(YEAR(A2),2)))
G3: =IF(A3="","",IF(A3>=DATE(YEAR(A3),4,6),YEAR(A3)&"-"&RIGHT(YEAR(A3)+1,2),YEAR(A3)-1&"-"&RIGHT(YEAR(A3),2)))
G4: =IF(A4="","",IF(A4>=DATE(YEAR(A4),4,6),YEAR(A4)&"-"&RIGHT(YEAR(A4)+1,2),YEAR(A4)-1&"-"&RIGHT(YEAR(A4),2)))
G5: =IF(A5="","",IF(A5>=DATE(YEAR(A5),4,6),YEAR(A5)&"-"&RIGHT(YEAR(A5)+1,2),YEAR(A5)-1&"-"&RIGHT(YEAR(A5),2)))
G6: =IF(A6="","",IF(A6>=DATE(YEAR(A6),4,6),YEAR(A6)&"-"&RIGHT(YEAR(A6)+1,2),YEAR(A6)-1&"-"&RIGHT(YEAR(A6),2)))
G7: =IF(A7="","",IF(A7>=DATE(YEAR(A7),4,6),YEAR(A7)&"-"&RIGHT(YEAR(A7)+1,2),YEAR(A7)-1&"-"&RIGHT(YEAR(A7),2)))
G8: =IF(A8="","",IF(A8>=DATE(YEAR(A8),4,6),YEAR(A8)&"-"&RIGHT(YEAR(A8)+1,2),YEAR(A8)-1&"-"&RIGHT(YEAR(A8),2)))
G9: =IF(A9="","",IF(A9>=DATE(YEAR(A9),4,6),YEAR(A9)&"-"&RIGHT(YEAR(A9)+1,2),YEAR(A9)-1&"-"&RIGHT(YEAR(A9),2)))
G10: =IF(A10="","",IF(A10>=DATE(YEAR(A10),4,6),YEAR(A10)&"-"&RIGHT(YEAR(A10)+1,2),YEAR(A10)-1&"-"&RIGHT(YEAR(A10),2)))
G11: =IF(A11="","",IF(A11>=DATE(YEAR(A11),4,6),YEAR(A11)&"-"&RIGHT(YEAR(A11)+1,2),YEAR(A11)-1&"-"&RIGHT(YEAR(A11),2)))
G12: =IF(A12="","",IF(A12>=DATE(YEAR(A12),4,6),YEAR(A12)&"-"&RIGHT(YEAR(A12)+1,2),YEAR(A12)-1&"-"&RIGHT(YEAR(A12),2)))
G13: =IF(A13="","",IF(A13>=DATE(YEAR(A13),4,6),YEAR(A13)&"-"&RIGHT(YEAR(A13)+1,2),YEAR(A13)-1&"-"&RIGHT(YEAR(A13),2)))
... G501: =IF(A501="","",IF(A501>=DATE(YEAR(A501),4,6),YEAR(A501)&"-"&RIGHT(YEAR(A501)+1,2),YEAR(A501)-1&"-"&RIGHT(YEAR(A501),2)))

Sheet Summary
A1: Tax year (type as 2026-27) | B1: 2026-27
A3: Platform | B3: Sales | C3: Fees | D3: Postage | E3: Item costs | F3: Profit
A4: eBay | B4: =SUMIFS(Sales!E:E,Sales!B:B,"eBay",Sales!J:J,$B$1) | C4: =SUMIFS(Sales!F:F,Sales!B:B,"eBay",Sales!J:J,$B$1) | D4: =SUMIFS(Sales!G:G,Sales!B:B,"eBay",Sales!J:J,$B$1) | E4: =SUMIFS(Sales!H:H,Sales!B:B,"eBay",Sales!J:J,$B$1) | F4: =B4-C4-D4-E4
A5: Amazon | B5: =SUMIFS(Sales!E:E,Sales!B:B,"Amazon",Sales!J:J,$B$1) | C5: =SUMIFS(Sales!F:F,Sales!B:B,"Amazon",Sales!J:J,$B$1) | D5: =SUMIFS(Sales!G:G,Sales!B:B,"Amazon",Sales!J:J,$B$1) | E5: =SUMIFS(Sales!H:H,Sales!B:B,"Amazon",Sales!J:J,$B$1) | F5: =B5-C5-D5-E5
A6: Vinted | B6: =SUMIFS(Sales!E:E,Sales!B:B,"Vinted",Sales!J:J,$B$1) | C6: =SUMIFS(Sales!F:F,Sales!B:B,"Vinted",Sales!J:J,$B$1) | D6: =SUMIFS(Sales!G:G,Sales!B:B,"Vinted",Sales!J:J,$B$1) | E6: =SUMIFS(Sales!H:H,Sales!B:B,"Vinted",Sales!J:J,$B$1) | F6: =B6-C6-D6-E6
A7: Facebook | B7: =SUMIFS(Sales!E:E,Sales!B:B,"Facebook",Sales!J:J,$B$1) | C7: =SUMIFS(Sales!F:F,Sales!B:B,"Facebook",Sales!J:J,$B$1) | D7: =SUMIFS(Sales!G:G,Sales!B:B,"Facebook",Sales!J:J,$B$1) | E7: =SUMIFS(Sales!H:H,Sales!B:B,"Facebook",Sales!J:J,$B$1) | F7: =B7-C7-D7-E7
A8: Depop | B8: =SUMIFS(Sales!E:E,Sales!B:B,"Depop",Sales!J:J,$B$1) | C8: =SUMIFS(Sales!F:F,Sales!B:B,"Depop",Sales!J:J,$B$1) | D8: =SUMIFS(Sales!G:G,Sales!B:B,"Depop",Sales!J:J,$B$1) | E8: =SUMIFS(Sales!H:H,Sales!B:B,"Depop",Sales!J:J,$B$1) | F8: =B8-C8-D8-E8
A9: Etsy | B9: =SUMIFS(Sales!E:E,Sales!B:B,"Etsy",Sales!J:J,$B$1) | C9: =SUMIFS(Sales!F:F,Sales!B:B,"Etsy",Sales!J:J,$B$1) | D9: =SUMIFS(Sales!G:G,Sales!B:B,"Etsy",Sales!J:J,$B$1) | E9: =SUMIFS(Sales!H:H,Sales!B:B,"Etsy",Sales!J:J,$B$1) | F9: =B9-C9-D9-E9
A10: Whatnot | B10: =SUMIFS(Sales!E:E,Sales!B:B,"Whatnot",Sales!J:J,$B$1) | C10: =SUMIFS(Sales!F:F,Sales!B:B,"Whatnot",Sales!J:J,$B$1) | D10: =SUMIFS(Sales!G:G,Sales!B:B,"Whatnot",Sales!J:J,$B$1) | E10: =SUMIFS(Sales!H:H,Sales!B:B,"Whatnot",Sales!J:J,$B$1) | F10: =B10-C10-D10-E10
A11: TikTok Shop | B11: =SUMIFS(Sales!E:E,Sales!B:B,"TikTok Shop",Sales!J:J,$B$1) | C11: =SUMIFS(Sales!F:F,Sales!B:B,"TikTok Shop",Sales!J:J,$B$1) | D11: =SUMIFS(Sales!G:G,Sales!B:B,"TikTok Shop",Sales!J:J,$B$1) | E11: =SUMIFS(Sales!H:H,Sales!B:B,"TikTok Shop",Sales!J:J,$B$1) | F11: =B11-C11-D11-E11
A12: Own site | B12: =SUMIFS(Sales!E:E,Sales!B:B,"Own site",Sales!J:J,$B$1) | C12: =SUMIFS(Sales!F:F,Sales!B:B,"Own site",Sales!J:J,$B$1) | D12: =SUMIFS(Sales!G:G,Sales!B:B,"Own site",Sales!J:J,$B$1) | E12: =SUMIFS(Sales!H:H,Sales!B:B,"Own site",Sales!J:J,$B$1) | F12: =B12-C12-D12-E12
A13: Other | B13: =SUMIFS(Sales!E:E,Sales!B:B,"Other",Sales!J:J,$B$1) | C13: =SUMIFS(Sales!F:F,Sales!B:B,"Other",Sales!J:J,$B$1) | D13: =SUMIFS(Sales!G:G,Sales!B:B,"Other",Sales!J:J,$B$1) | E13: =SUMIFS(Sales!H:H,Sales!B:B,"Other",Sales!J:J,$B$1) | F13: =B13-C13-D13-E13
A14: All platforms | B14: =SUMIFS(Sales!E:E,Sales!J:J,$B$1) | C14: =SUMIFS(Sales!F:F,Sales!J:J,$B$1) | D14: =SUMIFS(Sales!G:G,Sales!J:J,$B$1) | E14: =SUMIFS(Sales!H:H,Sales!J:J,$B$1) | F14: =B14-C14-D14-E14
A16: Expenses | F16: =-SUMIFS(Expenses!E:E,Expenses!G:G,$B$1)
A17: Profit after expenses | F17: =F14+F16
A19: Sales count this tax year | F19: =COUNTIFS(Sales!J:J,$B$1)
